zibanu/__init__.py
zibanu/django/__init__.py
zibanu/django/apps.py
zibanu/django/urls.py
zibanu/django/api/__init__.py
zibanu/django/api/services/__init__.py
zibanu/django/api/services/dial_codes.py
zibanu/django/api/services/language.py
zibanu/django/api/services/timezone.py
zibanu/django/db/__init__.py
zibanu/django/db/backends/__init__.py
zibanu/django/db/backends/oracle/__init__.py
zibanu/django/db/backends/oracle/base.py
zibanu/django/db/models/__init__.py
zibanu/django/db/models/dated_model.py
zibanu/django/db/models/manager.py
zibanu/django/db/models/model.py
zibanu/django/db/models/fields/__init__.py
zibanu/django/db/models/fields/phone_field.py
zibanu/django/lib/__init__.py
zibanu/django/lib/classes/__init__.py
zibanu/django/lib/classes/base_model_controller.py
zibanu/django/lib/classes/code_generator.py
zibanu/django/lib/classes/extended_json_encoder.py
zibanu/django/lib/classes/model_name.py
zibanu/django/lib/classes/regex.py
zibanu/django/lib/enums/__init__.py
zibanu/django/lib/enums/dial_codes.py
zibanu/django/lib/metaclasses/__init__.py
zibanu/django/lib/metaclasses/model_controller.py
zibanu/django/lib/utils/__init__.py
zibanu/django/lib/utils/date_time.py
zibanu/django/lib/utils/error_messages.py
zibanu/django/lib/utils/file_utils.py
zibanu/django/lib/utils/generic_utils.py
zibanu/django/lib/utils/mail.py
zibanu/django/lib/utils/model_utils.py
zibanu/django/lib/utils/receivers_utils.py
zibanu/django/lib/utils/request_utils.py
zibanu/django/lib/utils/user_utils.py
zibanu/django/locale/es/LC_MESSAGES/django.mo
zibanu/django/locale/es/LC_MESSAGES/django.po
zibanu/django/rest_framework/__init__.py
zibanu/django/rest_framework/decorators.py
zibanu/django/rest_framework/utils.py
zibanu/django/rest_framework/exceptions/__init__.py
zibanu/django/rest_framework/exceptions/api_exception.py
zibanu/django/rest_framework/exceptions/multiple_login_error.py
zibanu/django/rest_framework/exceptions/not_authenticated.py
zibanu_django-2.0.6.dist-info/licenses/LICENSE
zibanu_django-2.0.6.dist-info/METADATA
zibanu_django-2.0.6.dist-info/WHEEL
zibanu_django-2.0.6.dist-info/top_level.txt
zibanu_django-2.0.6.dist-info/RECORD
